[
  {
    "Type": "AthenaCharacterItemDefinition",
    "Name": "CID_803_Athena_Commando_F_SharkSuit",
    "Class": "UScriptClass'AthenaCharacterItemDefinition'",
    "Flags": "RF_Public | RF_Standalone | RF_Transactional | RF_WasLoaded | RF_LoadCompleted",
    "Properties": {
      "BaseCharacterParts": [
        {
          "AssetPathName": "/BRCosmetics/Characters/CharacterParts/FaceAccessories/CP_F_MED_SharkSuit_FaceAcc.CP_F_MED_SharkSuit_FaceAcc",
          "SubPathString": ""
        },
        {
          "AssetPathName": "/BRCosmetics/Characters/CharacterParts/Male/Medium/Heads/CP_Athena_Head_F_SharkSuit.CP_Athena_Head_F_SharkSuit",
          "SubPathString": ""
        },
        {
          "AssetPathName": "/BRCosmetics/Athena/Heroes/Meshes/Bodies/CP_Athena_Body_F_SharkSuit.CP_Athena_Body_F_SharkSuit",
          "SubPathString": ""
        }
      ],
      "Gender": "EFortCustomGender::Female",
      "DefaultMontageLookupTable": {
        "AssetPathName": "/Game/Animation/Game/MainPlayer/Menu/MontageLookUpTables/MediumFemale.MediumFemale",
        "SubPathString": ""
      },
      "MetaTags": [
        "Cosmetics.MetaTags.Special.BodySwap.Medium"
      ],
      "ItemVariants": [
        {
          "ObjectName": "FortCosmeticMaterialVariant'CID_803_Athena_Commando_F_SharkSuit:FortCosmeticMaterialVariant_1'",
          "ObjectPath": "/BRCosmetics/Athena/Items/Cosmetics/Characters/CID_803_Athena_Commando_F_SharkSuit.2"
        },
        {
          "ObjectName": "FortCosmeticMaterialVariant'CID_803_Athena_Commando_F_SharkSuit:FortCosmeticMaterialVariant_0'",
          "ObjectPath": "/BRCosmetics/Athena/Items/Cosmetics/Characters/CID_803_Athena_Commando_F_SharkSuit.1"
        },
        {
          "ObjectName": "FortCosmeticPropertyVariant'CID_803_Athena_Commando_F_SharkSuit:FortCosmeticPropertyVariant_1'",
          "ObjectPath": "/BRCosmetics/Athena/Items/Cosmetics/Characters/CID_803_Athena_Commando_F_SharkSuit.3"
        }
      ],
      "ItemVariantPreviews": [
        {
          "UnlockCondition": {
            "CultureInvariantString": null
          },
          "PreviewTime": 4.0,
          "VariantOptions": [
            {
              "OwnedVariantTags": [],
              "ItemVariantIsUsedFor": null,
              "CustomData": "",
              "VariantChannelTag": {
                "TagName": "Cosmetics.Variant.Channel.Material"
              },
              "ActiveVariantTag": {
                "TagName": "Cosmetics.Variant.Property.Mat2"
              }
            }
          ],
          "AdditionalItems": []
        },
        {
          "UnlockCondition": {
            "CultureInvariantString": null
          },
          "PreviewTime": 4.0,
          "VariantOptions": [
            {
              "OwnedVariantTags": [],
              "ItemVariantIsUsedFor": null,
              "CustomData": "",
              "VariantChannelTag": {
                "TagName": "Cosmetics.Variant.Channel.Parts"
              },
              "ActiveVariantTag": {
                "TagName": "Cosmetics.Variant.Property.Stage2"
              }
            }
          ],
          "AdditionalItems": []
        }
      ],
      "BaseShotGridId": 28907,
      "VariantShotGridIds": [
        67738
      ],
      "ShotGridIds": [
        28907,
        67738
      ],
      "Rarity": "EFortRarity::Rare",
      "ItemName": {
        "Namespace": "",
        "Key": "C81AEDA34701FF01A202F2958B48837A",
        "SourceString": "Cozy Chomps",
        "LocalizedString": "Cozy Chomps"
      },
      "ItemDescription": {
        "Namespace": "",
        "Key": "BDDB48D84BBE5EE5123B138995859C80",
        "SourceString": "Take life one chomp at a time.",
        "LocalizedString": "Take life one chomp at a time."
      },
      "ItemShortDescription": {
        "Namespace": "",
        "Key": "9658361F4EFF6B98FF153898E58C9D52",
        "SourceString": "Outfit",
        "LocalizedString": "Outfit"
      },
      "DataList": [
        {
          "LargeIcon": {
            "AssetPathName": "/BRCosmetics/UI/Foundation/Textures/Icons/Heroes/Athena/Soldier/T-Soldier-HID-803-Athena-Commando-F-SharkSuit-L.T-Soldier-HID-803-Athena-Commando-F-SharkSuit-L",
            "SubPathString": ""
          }
        },
        {
          "Icon": {
            "AssetPathName": "/BRCosmetics/UI/Foundation/Textures/Icons/Heroes/Athena/Soldier/T-Soldier-HID-803-Athena-Commando-F-SharkSuit.T-Soldier-HID-803-Athena-Commando-F-SharkSuit",
            "SubPathString": ""
          }
        },
        {
          "MinLevel": 1,
          "MaxLevel": 1
        },
        {
          "Tags": [
            "Cosmetics.Source.ItemShop",
            "Cosmetics.Filter.Season.13",
            "Cosmetics.Set.EatingCraze",
            "Cosmetics.UserFacingFlags.HasVariants",
            "SoundLibrary.ID.ClothingType.Generic",
            "SoundLibrary.ID.HandType.Glove",
            "SoundLibrary.ID.StepType.ShoesSneakers",
            "Cosmetics.FrontEndPose.DontHandsOnHips",
            "Cosmetics.Gating.Allow.Shoes"
          ]
        },
        {
          "Traits": [
            "Item.Trait.SingleStack"
          ]
        },
        {
          "GeneratedTagsIndexes": [
            115,
            543,
            549,
            7,
            552,
            7975,
            229,
            2,
            544,
            553,
            540,
            245,
            75,
            123,
            269,
            246,
            164,
            54,
            681,
            687,
            713,
            174,
            786,
            832,
            58,
            879,
            961,
            53,
            1080,
            104,
            1083,
            1555
          ]
        }
      ]
    }
  },
  {
    "Type": "FortCosmeticMaterialVariant",
    "Name": "FortCosmeticMaterialVariant_0",
    "Outer": "CID_803_Athena_Commando_F_SharkSuit",
    "Class": "UScriptClass'FortCosmeticMaterialVariant'",
    "Flags": "RF_Public | RF_Transactional | RF_WasLoaded | RF_LoadCompleted",
    "Properties": {
      "MaterialOptions": [
        {
          "VariantMaterials": [],
          "VariantMaterialParams": [],
          "VariantSounds": [],
          "VariantFoley": [],
          "CosmeticProperties": [],
          "MetaTags": {
            "MetaTagsToApply": [],
            "MetaTagsToRemove": []
          },
          "bStartUnlocked": true,
          "bIsDefault": true,
          "bHideIfNotOwned": false,
          "CustomizationVariantTag": {
            "TagName": "Cosmetics.Variant.Property.Mat1"
          },
          "VariantName": {
            "Namespace": "",
            "Key": "BA9647AC4A3FD041F7E990BE69CDFD52",
            "SourceString": "DEFAULT",
            "LocalizedString": "DEFAULT"
          },
          "PreviewImage": {
            "AssetPathName": "/BRCosmetics/UI/Foundation/Textures/Icons/Heroes/Variants/T-Variant-803-F-SharkSuit.T-Variant-803-F-SharkSuit",
            "SubPathString": ""
          },
          "UnlockRequirements": {
            "CultureInvariantString": null
          },
          "UnlockingItemDef": {
            "AssetPathName": "",
            "SubPathString": ""
          },
          "VariantGameplayTags": []
        },
        {
          "VariantMaterials": [],
          "VariantMaterialParams": [
            {
              "MaterialsToAlter": [
                {
                  "AssetPathName": "/BRCosmetics/Characters/Player/Female/Medium/Bodies/F_MED_Shark_Suit/Materials/F_MED_SharkSuit_Body.F_MED_SharkSuit_Body",
                  "SubPathString": ""
                }
              ],
              "CascadeMaterialName": "None",
              "ColorParams": [],
              "TextureParams": [],
              "FloatParams": [
                {
                  "Value": 1.0,
                  "ParamName": "Hide Element 09"
                }
              ],
              "MaterialToAlter": {
                "AssetPathName": "/BRCosmetics/Characters/Player/Female/Medium/Bodies/F_MED_Shark_Suit/Materials/F_MED_SharkSuit_Body.F_MED_SharkSuit_Body",
                "SubPathString": ""
              }
            },
            {
              "MaterialsToAlter": [
                {
                  "AssetPathName": "/BRCosmetics/Characters/Player/Female/Medium/Bodies/F_MED_Shark_Suit/Skins/Stripe/Materials/F_MED_SharkSuit_Body.F_MED_SharkSuit_Body",
                  "SubPathString": ""
                }
              ],
              "CascadeMaterialName": "None",
              "ColorParams": [],
              "TextureParams": [],
              "FloatParams": [
                {
                  "Value": 1.0,
                  "ParamName": "Hide Element 09"
                }
              ],
              "MaterialToAlter": {
                "AssetPathName": "/BRCosmetics/Characters/Player/Female/Medium/Bodies/F_MED_Shark_Suit/Skins/Stripe/Materials/F_MED_SharkSuit_Body.F_MED_SharkSuit_Body",
                "SubPathString": ""
              }
            }
          ],
          "VariantSounds": [],
          "VariantFoley": [],
          "CosmeticProperties": [],
          "MetaTags": {
            "MetaTagsToApply": [
              "Cosmetics.Variant.Property.Mat2"
            ],
            "MetaTagsToRemove": []
          },
          "bStartUnlocked": true,
          "bIsDefault": false,
          "bHideIfNotOwned": false,
          "CustomizationVariantTag": {
            "TagName": "Cosmetics.Variant.Property.Mat2"
          },
          "VariantName": {
            "Namespace": "",
            "Key": "233740D74C1BEBE7A56BBEB0FC63E0A8",
            "SourceString": "NO TAIL",
            "LocalizedString": "NO TAIL"
          },
          "PreviewImage": {
            "AssetPathName": "/BRCosmetics/UI/Foundation/Textures/Icons/Heroes/Variants/T-Variant-803-F-SharkSuit-NoTail.T-Variant-803-F-SharkSuit-NoTail",
            "SubPathString": ""
          },
          "UnlockRequirements": {
            "CultureInvariantString": null
          },
          "UnlockingItemDef": {
            "AssetPathName": "",
            "SubPathString": ""
          },
          "VariantGameplayTags": []
        }
      ],
      "VariantChannelName": {
        "Namespace": "",
        "Key": "CF38724B438EDE415C9390B79A29BAFC",
        "SourceString": "tail",
        "LocalizedString": "tail"
      },
      "VariantChannelTag": {
        "TagName": "Cosmetics.Variant.Channel.Material"
      }
    }
  },
  {
    "Type": "FortCosmeticMaterialVariant",
    "Name": "FortCosmeticMaterialVariant_1",
    "Outer": "CID_803_Athena_Commando_F_SharkSuit",
    "Class": "UScriptClass'FortCosmeticMaterialVariant'",
    "Flags": "RF_Public | RF_Transactional | RF_WasLoaded | RF_LoadCompleted",
    "Properties": {
      "MaterialOptions": [
        {
          "VariantMaterials": [],
          "VariantMaterialParams": [],
          "VariantSounds": [],
          "VariantFoley": [],
          "CosmeticProperties": [],
          "MetaTags": {
            "MetaTagsToApply": [],
            "MetaTagsToRemove": []
          },
          "bStartUnlocked": true,
          "bIsDefault": true,
          "bHideIfNotOwned": false,
          "CustomizationVariantTag": {
            "TagName": "Cosmetics.Variant.Property.Stage1"
          },
          "VariantName": {
            "Namespace": "",
            "Key": "DF6B1F594BB59D603A825B815A84D2E0",
            "SourceString": "Cozy Chomps",
            "LocalizedString": "Cozy Chomps"
          },
          "PreviewImage": {
            "AssetPathName": "/BRCosmetics/UI/Foundation/Textures/Icons/Heroes/Athena/Soldier/T-Soldier-HID-803-Athena-Commando-F-SharkSuit.T-Soldier-HID-803-Athena-Commando-F-SharkSuit",
            "SubPathString": ""
          },
          "UnlockRequirements": {
            "CultureInvariantString": null
          },
          "UnlockingItemDef": {
            "AssetPathName": "",
            "SubPathString": ""
          },
          "VariantGameplayTags": []
        },
        {
          "VariantMaterials": [
            {
              "MaterialToSwap": {
                "AssetPathName": "/BRCosmetics/Characters/Player/Female/Medium/Bodies/F_MED_Shark_Suit/Materials/F_MED_SharkSuit_Body.F_MED_SharkSuit_Body",
                "SubPathString": ""
              },
              "ComponentToOverride": "None",
              "CascadeMaterialName": "None",
              "MaterialOverrideIndex": 0,
              "OverrideMaterial": {
                "AssetPathName": "/BRCosmetics/Characters/Player/Female/Medium/Bodies/F_MED_Shark_Suit/Skins/Stripe/Materials/F_MED_SharkSuit_Body.F_MED_SharkSuit_Body",
                "SubPathString": ""
              }
            }
          ],
          "VariantMaterialParams": [],
          "VariantSounds": [],
          "VariantFoley": [],
          "CosmeticProperties": [
            {
              "OverrideMaterialParams": null,
              "AdditionalScalarParameters": [],
              "AdditionalVectorParameters": [
                {
                  "ParameterInfo": {
                    "Name": "SockPrimaryColor",
                    "Association": "EMaterialParameterAssociation::GlobalParameter",
                    "Index": -1
                  },
                  "ParameterValue": {
                    "R": 0.300544,
                    "G": 0.270498,
                    "B": 0.287441,
                    "A": 1.0,
                    "Hex": "958E92"
                  },
                  "ExpressionGUID": "00000000-00000000-00000000-00000000"
                },
                {
                  "ParameterInfo": {
                    "Name": "SockPrimarySRMF",
                    "Association": "EMaterialParameterAssociation::GlobalParameter",
                    "Index": -1
                  },
                  "ParameterValue": {
                    "R": 0.55,
                    "G": 0.6,
                    "B": 0.6,
                    "A": 0.0,
                    "Hex": "C4CCCC"
                  },
                  "ExpressionGUID": "00000000-00000000-00000000-00000000"
                }
              ],
              "AdditionalTextureParameters": [],
              "bAttemptVariantInfoTransfer": false,
              "MaterialParameterNameForVariantInfo": "None",
              "PropertyTag": {
                "TagName": "CosmeticProperty.MorphOverrideData"
              }
            }
          ],
          "MetaTags": {
            "MetaTagsToApply": [],
            "MetaTagsToRemove": []
          },
          "bStartUnlocked": true,
          "bIsDefault": false,
          "bHideIfNotOwned": false,
          "CustomizationVariantTag": {
            "TagName": "Cosmetics.Variant.Property.Stage2"
          },
          "VariantName": {
            "Namespace": "",
            "Key": "F2F33C86481F7925534B45AFDE234034",
            "SourceString": "Pyjama Shark",
            "LocalizedString": "Pyjama Shark"
          },
          "PreviewImage": {
            "AssetPathName": "/BRCosmetics/UI/Foundation/Textures/Icons/Heroes/Variants/T-Soldier-HID-803-Athena-Commando-F-SharkSuit-Stripe.T-Soldier-HID-803-Athena-Commando-F-SharkSuit-Stripe",
            "SubPathString": ""
          },
          "UnlockRequirements": {
            "CultureInvariantString": null
          },
          "UnlockingItemDef": {
            "AssetPathName": "",
            "SubPathString": ""
          },
          "VariantGameplayTags": []
        }
      ],
      "VariantChannelName": {
        "Namespace": "",
        "Key": "95ABF5CC40E9147B7802D098A53E81EA",
        "SourceString": "style",
        "LocalizedString": "style"
      },
      "VariantChannelTag": {
        "TagName": "Cosmetics.Variant.Channel.Parts"
      }
    }
  },
  {
    "Type": "FortCosmeticPropertyVariant",
    "Name": "FortCosmeticPropertyVariant_1",
    "Outer": "CID_803_Athena_Commando_F_SharkSuit",
    "Class": "UScriptClass'FortCosmeticPropertyVariant'",
    "Flags": "RF_WasLoaded | RF_LoadCompleted",
    "Properties": {
      "GenericPropertyOptions": [
        {
          "CosmeticProperties": [
            {
              "AssembledMeshSchema": {
                "AssetPathName": "",
                "SubPathString": ""
              },
              "PropertyTag": {
                "TagName": "Cosmetics.Variant.Property.FigureDetailsLevel"
              }
            }
          ],
          "MetaTags": {
            "MetaTagsToApply": [],
            "MetaTagsToRemove": []
          },
          "bStartUnlocked": true,
          "bIsDefault": true,
          "bHideIfNotOwned": false,
          "CustomizationVariantTag": {
            "TagName": "Cosmetics.Variant.Property.FigureDetailsLevel.Signature"
          },
          "VariantName": {
            "Namespace": "JunoAccountItemsConversionTypes",
            "Key": "FigureDetailsLevelSignature",
            "SourceString": "Signature",
            "LocalizedString": "Signature"
          },
          "PreviewImage": {
            "AssetPathName": "",
            "SubPathString": ""
          },
          "UnlockRequirements": {
            "CultureInvariantString": null
          },
          "UnlockingItemDef": {
            "AssetPathName": "",
            "SubPathString": ""
          },
          "VariantGameplayTags": []
        },
        {
          "CosmeticProperties": [
            {
              "AssembledMeshSchema": {
                "AssetPathName": "",
                "SubPathString": ""
              },
              "PropertyTag": {
                "TagName": "Cosmetics.Variant.Property.FigureDetailsLevel"
              }
            }
          ],
          "MetaTags": {
            "MetaTagsToApply": [],
            "MetaTagsToRemove": []
          },
          "bStartUnlocked": true,
          "bIsDefault": false,
          "bHideIfNotOwned": false,
          "CustomizationVariantTag": {
            "TagName": "Cosmetics.Variant.Property.FigureDetailsLevel.Simple"
          },
          "VariantName": {
            "Namespace": "JunoAccountItemsConversionTypes",
            "Key": "FigureDetailsLevelSimple",
            "SourceString": "Base",
            "LocalizedString": "Base"
          },
          "PreviewImage": {
            "AssetPathName": "",
            "SubPathString": ""
          },
          "UnlockRequirements": {
            "CultureInvariantString": null
          },
          "UnlockingItemDef": {
            "AssetPathName": "",
            "SubPathString": ""
          },
          "VariantGameplayTags": []
        }
      ],
      "VariantChannelName": {
        "Namespace": "JunoAccountItemsConversionTypes",
        "Key": "FigureDetailsLevelChannelName",
        "SourceString": "LEGO® Style",
        "LocalizedString": "LEGO® Style"
      },
      "ProductTags": [
        {
          "TagName": "Product.Juno"
        }
      ],
      "VariantChannelTag": {
        "TagName": "Cosmetics.Variant.Channel.FigureDetailsLevel"
      }
    }
  }
]