[
  {
    "Type": "AthenaCharacterItemDefinition",
    "Name": "CID_A_438_Athena_Commando_F_Gloom",
    "Class": "UScriptClass'AthenaCharacterItemDefinition'",
    "Flags": "RF_Public | RF_Standalone | RF_Transactional | RF_WasLoaded | RF_LoadCompleted",
    "Properties": {
      "BaseCharacterParts": [
        {
          "AssetPathName": "/BRCosmetics/Characters/CharacterParts/Female/Medium/Heads/CP_Athena_Head_F_Gloom.CP_Athena_Head_F_Gloom",
          "SubPathString": ""
        },
        {
          "AssetPathName": "/BRCosmetics/Athena/Heroes/Meshes/Bodies/CP_Athena_Body_F_Gloom.CP_Athena_Body_F_Gloom",
          "SubPathString": ""
        },
        {
          "AssetPathName": "/BRCosmetics/Characters/CharacterParts/FaceAccessories/CP_F_MED_Gloom_FaceAcc.CP_F_MED_Gloom_FaceAcc",
          "SubPathString": ""
        }
      ],
      "Gender": "EFortCustomGender::Female",
      "DefaultMontageLookupTable": {
        "AssetPathName": "/Game/Animation/Game/MainPlayer/Menu/MontageLookUpTables/MediumFemale.MediumFemale",
        "SubPathString": ""
      },
      "ItemVariants": [
        {
          "ObjectName": "FortCosmeticCharacterPartVariant'CID_A_438_Athena_Commando_F_Gloom:FortCosmeticCharacterPartVariant_1'",
          "ObjectPath": "/BRCosmetics/Athena/Items/Cosmetics/Characters/CID_A_438_Athena_Commando_F_Gloom.2"
        },
        {
          "ObjectName": "FortCosmeticCharacterPartVariant'CID_A_438_Athena_Commando_F_Gloom:FortCosmeticCharacterPartVariant_0'",
          "ObjectPath": "/BRCosmetics/Athena/Items/Cosmetics/Characters/CID_A_438_Athena_Commando_F_Gloom.1"
        },
        {
          "ObjectName": "FortCosmeticPropertyVariant'CID_A_438_Athena_Commando_F_Gloom:FortCosmeticPropertyVariant_1'",
          "ObjectPath": "/BRCosmetics/Athena/Items/Cosmetics/Characters/CID_A_438_Athena_Commando_F_Gloom.3"
        }
      ],
      "BaseShotGridId": 56393,
      "VariantShotGridIds": [
        58217
      ],
      "ShotGridIds": [
        56393,
        58217
      ],
      "Rarity": "EFortRarity::Epic",
      "ItemName": {
        "Namespace": "",
        "Key": "63E3FFBF4CEF6FE785156F9E021E6005",
        "SourceString": "Phaedra",
        "LocalizedString": "Phaedra"
      },
      "ItemDescription": {
        "Namespace": "",
        "Key": "17DB9616430DE9A6DD686DA8A2E3D679",
        "SourceString": "A dark sea witch with unknowable power.",
        "LocalizedString": "A dark sea witch with unknowable power."
      },
      "ItemShortDescription": {
        "Namespace": "",
        "Key": "9658361F4EFF6B98FF153898E58C9D52",
        "SourceString": "Outfit",
        "LocalizedString": "Outfit"
      },
      "DataList": [
        {
          "LargeIcon": {
            "AssetPathName": "/BRCosmetics/UI/Foundation/Textures/Icons/Heroes/Athena/Soldier/T-Soldier-HID-A-438-Athena-Commando-F-Gloom-L.T-Soldier-HID-A-438-Athena-Commando-F-Gloom-L",
            "SubPathString": ""
          }
        },
        {
          "Icon": {
            "AssetPathName": "/BRCosmetics/UI/Foundation/Textures/Icons/Heroes/Athena/Soldier/T-Soldier-HID-A-438-Athena-Commando-F-Gloom.T-Soldier-HID-A-438-Athena-Commando-F-Gloom",
            "SubPathString": ""
          }
        },
        {
          "MinLevel": 1,
          "MaxLevel": 1
        },
        {
          "Tags": [
            "Cosmetics.UserFacingFlags.HasVariants",
            "Cosmetics.Filter.Season.21",
            "Cosmetics.Set.EerieBoats",
            "SoundLibrary.ID.StepType.BootsCombat",
            "SoundLibrary.ID.ClothingType.Generic",
            "SoundLibrary.ID.HandType.Glove",
            "Cosmetics.Gating.Allow.Shoes"
          ]
        },
        {
          "Traits": [
            "Item.Trait.SingleStack"
          ]
        },
        {
          "GeneratedTagsIndexes": [
            550,
            543,
            552,
            7975,
            236,
            544,
            614,
            584,
            588,
            581,
            586,
            242,
            19,
            269,
            536,
            784,
            787,
            793,
            1118,
            108,
            2040,
            2420
          ]
        },
        {
          "Series": {
            "ObjectName": "FortItemSeriesDefinition'CrewSeries'",
            "ObjectPath": "/Game/Athena/Items/Cosmetics/Series/CrewSeries.0"
          }
        }
      ]
    }
  },
  {
    "Type": "FortCosmeticCharacterPartVariant",
    "Name": "FortCosmeticCharacterPartVariant_0",
    "Outer": "CID_A_438_Athena_Commando_F_Gloom",
    "Class": "UScriptClass'FortCosmeticCharacterPartVariant'",
    "Flags": "RF_Public | RF_Transactional | RF_WasLoaded | RF_LoadCompleted",
    "Properties": {
      "PartOptions": [
        {
          "VariantParts": [],
          "VariantMaterials": [],
          "VariantMaterialParams": [],
          "InitalParticleSystemData": [],
          "VariantParticles": [],
          "VariantParticleParams": [],
          "VariantSounds": [],
          "VariantFoley": [],
          "SocketTransforms": [],
          "VariantActions": [],
          "VariantMeshes": [],
          "CosmeticProperties": [],
          "MetaTags": {
            "MetaTagsToApply": [],
            "MetaTagsToRemove": []
          },
          "bStartUnlocked": true,
          "bIsDefault": true,
          "bHideIfNotOwned": false,
          "CustomizationVariantTag": {
            "TagName": "Cosmetics.Variant.Property.Stage1"
          },
          "VariantName": {
            "Namespace": "",
            "Key": "537D47FF4227C8D73791F5A5F963E8A6",
            "SourceString": "off",
            "LocalizedString": "off"
          },
          "PreviewImage": {
            "AssetPathName": "/BRCosmetics/UI/Foundation/Textures/Icons/Heroes/Variants/T-Variant-A-438-F-Gloom-Legs-FishnetsOff.T-Variant-A-438-F-Gloom-Legs-FishnetsOff",
            "SubPathString": ""
          },
          "UnlockRequirements": {
            "CultureInvariantString": null
          },
          "UnlockingItemDef": {
            "AssetPathName": "",
            "SubPathString": ""
          },
          "VariantGameplayTags": []
        },
        {
          "VariantParts": [],
          "VariantMaterials": [
            {
              "MaterialToSwap": {
                "AssetPathName": "/BRCosmetics/Characters/Player/Female/Medium/Bodies/F_MED_Gloom/Material/F_MED_Gloom_Body.F_MED_Gloom_Body",
                "SubPathString": ""
              },
              "ComponentToOverride": "None",
              "CascadeMaterialName": "None",
              "MaterialOverrideIndex": 0,
              "OverrideMaterial": {
                "AssetPathName": "/BRCosmetics/Characters/Player/Female/Medium/Bodies/F_MED_Gloom/Skins/Alt/Materials/F_MED_Gloom_Alt_Body.F_MED_Gloom_Alt_Body",
                "SubPathString": ""
              }
            }
          ],
          "VariantMaterialParams": [],
          "InitalParticleSystemData": [],
          "VariantParticles": [],
          "VariantParticleParams": [],
          "VariantSounds": [],
          "VariantFoley": [],
          "SocketTransforms": [],
          "VariantActions": [],
          "VariantMeshes": [],
          "CosmeticProperties": [],
          "MetaTags": {
            "MetaTagsToApply": [],
            "MetaTagsToRemove": []
          },
          "bStartUnlocked": true,
          "bIsDefault": false,
          "bHideIfNotOwned": false,
          "CustomizationVariantTag": {
            "TagName": "Cosmetics.Variant.Property.Stage2"
          },
          "VariantName": {
            "Namespace": "",
            "Key": "96A718FA4847461D5617DD937D24493D",
            "SourceString": "on",
            "LocalizedString": "on"
          },
          "PreviewImage": {
            "AssetPathName": "/BRCosmetics/UI/Foundation/Textures/Icons/Heroes/Variants/T-Variant-A-438-F-Gloom-Legs-Fishnets.T-Variant-A-438-F-Gloom-Legs-Fishnets",
            "SubPathString": ""
          },
          "UnlockRequirements": {
            "CultureInvariantString": null
          },
          "UnlockingItemDef": {
            "AssetPathName": "",
            "SubPathString": ""
          },
          "VariantGameplayTags": []
        }
      ],
      "VariantChannelName": {
        "Namespace": "",
        "Key": "F5DED52B4B3AEC07461F4EB1FE791503",
        "SourceString": "fishnets",
        "LocalizedString": "fishnets"
      },
      "VariantChannelTag": {
        "TagName": "Cosmetics.Variant.Channel.Parts"
      }
    }
  },
  {
    "Type": "FortCosmeticCharacterPartVariant",
    "Name": "FortCosmeticCharacterPartVariant_1",
    "Outer": "CID_A_438_Athena_Commando_F_Gloom",
    "Class": "UScriptClass'FortCosmeticCharacterPartVariant'",
    "Flags": "RF_Public | RF_Transactional | RF_WasLoaded | RF_LoadCompleted",
    "Properties": {
      "PartOptions": [
        {
          "VariantParts": [
            {
              "AssetPathName": "/BRCosmetics/Athena/Heroes/Meshes/Bodies/CP_Athena_Body_F_Gloom.CP_Athena_Body_F_Gloom",
              "SubPathString": ""
            }
          ],
          "VariantMaterials": [],
          "VariantMaterialParams": [
            {
              "MaterialsToAlter": [
                {
                  "AssetPathName": "/BRCosmetics/Characters/Player/Female/Medium/Bodies/F_MED_Gloom/Material/F_MED_Gloom_Body.F_MED_Gloom_Body",
                  "SubPathString": ""
                }
              ],
              "CascadeMaterialName": "None",
              "ColorParams": [],
              "TextureParams": [],
              "FloatParams": [
                {
                  "Value": 1.0,
                  "ParamName": "Hide Element 01"
                }
              ],
              "MaterialToAlter": {
                "AssetPathName": "/BRCosmetics/Characters/Player/Female/Medium/Bodies/F_MED_Gloom/Material/F_MED_Gloom_Body.F_MED_Gloom_Body",
                "SubPathString": ""
              }
            },
            {
              "MaterialsToAlter": [
                {
                  "AssetPathName": "/BRCosmetics/Characters/Player/Female/Medium/Bodies/F_MED_Gloom/Skins/Alt/Materials/F_MED_Gloom_Alt_Body.F_MED_Gloom_Alt_Body",
                  "SubPathString": ""
                }
              ],
              "CascadeMaterialName": "None",
              "ColorParams": [],
              "TextureParams": [],
              "FloatParams": [
                {
                  "Value": 1.0,
                  "ParamName": "Hide Element 01"
                }
              ],
              "MaterialToAlter": {
                "AssetPathName": "/BRCosmetics/Characters/Player/Female/Medium/Bodies/F_MED_Gloom/Skins/Alt/Materials/F_MED_Gloom_Alt_Body.F_MED_Gloom_Alt_Body",
                "SubPathString": ""
              }
            }
          ],
          "InitalParticleSystemData": [],
          "VariantParticles": [],
          "VariantParticleParams": [],
          "VariantSounds": [],
          "VariantFoley": [],
          "SocketTransforms": [],
          "VariantActions": [],
          "VariantMeshes": [],
          "CosmeticProperties": [],
          "MetaTags": {
            "MetaTagsToApply": [],
            "MetaTagsToRemove": []
          },
          "bStartUnlocked": true,
          "bIsDefault": true,
          "bHideIfNotOwned": false,
          "CustomizationVariantTag": {
            "TagName": "Cosmetics.Variant.Property.Stage1"
          },
          "VariantName": {
            "Namespace": "",
            "Key": "70E43A1841E30A47C1822CBB298063FE",
            "SourceString": "Phaedra",
            "LocalizedString": "Phaedra"
          },
          "PreviewImage": {
            "AssetPathName": "/BRCosmetics/UI/Foundation/Textures/Icons/Heroes/Athena/Soldier/T-Soldier-HID-A-438-Athena-Commando-F-Gloom.T-Soldier-HID-A-438-Athena-Commando-F-Gloom",
            "SubPathString": ""
          },
          "UnlockRequirements": {
            "CultureInvariantString": null
          },
          "UnlockingItemDef": {
            "AssetPathName": "",
            "SubPathString": ""
          },
          "VariantGameplayTags": []
        },
        {
          "VariantParts": [
            {
              "AssetPathName": "/BRCosmetics/Athena/Heroes/Meshes/Bodies/CP_Athena_Body_F_Gloom_Alt.CP_Athena_Body_F_Gloom_Alt",
              "SubPathString": ""
            }
          ],
          "VariantMaterials": [],
          "VariantMaterialParams": [],
          "InitalParticleSystemData": [],
          "VariantParticles": [],
          "VariantParticleParams": [],
          "VariantSounds": [],
          "VariantFoley": [],
          "SocketTransforms": [],
          "VariantActions": [],
          "VariantMeshes": [],
          "CosmeticProperties": [],
          "MetaTags": {
            "MetaTagsToApply": [
              "Cosmetics.Character.RestrictCape"
            ],
            "MetaTagsToRemove": []
          },
          "bStartUnlocked": true,
          "bIsDefault": false,
          "bHideIfNotOwned": false,
          "CustomizationVariantTag": {
            "TagName": "Cosmetics.Variant.Property.Stage2"
          },
          "VariantName": {
            "Namespace": "",
            "Key": "F98B8391498CC5662051378C3B18DB94",
            "SourceString": "Shrouded",
            "LocalizedString": "Shrouded"
          },
          "PreviewImage": {
            "AssetPathName": "/BRCosmetics/UI/Foundation/Textures/Icons/Heroes/Variants/T-Variant-A-438-F-Gloom-Shroud.T-Variant-A-438-F-Gloom-Shroud",
            "SubPathString": ""
          },
          "UnlockRequirements": {
            "CultureInvariantString": null
          },
          "UnlockingItemDef": {
            "AssetPathName": "",
            "SubPathString": ""
          },
          "VariantGameplayTags": []
        }
      ],
      "VariantChannelName": {
        "Namespace": "",
        "Key": "4EE4679841272A905F4DBFA827D012C0",
        "SourceString": "style",
        "LocalizedString": "style"
      },
      "VariantChannelTag": {
        "TagName": "Cosmetics.Variant.Channel.Material"
      }
    }
  },
  {
    "Type": "FortCosmeticPropertyVariant",
    "Name": "FortCosmeticPropertyVariant_1",
    "Outer": "CID_A_438_Athena_Commando_F_Gloom",
    "Class": "UScriptClass'FortCosmeticPropertyVariant'",
    "Flags": "RF_WasLoaded | RF_LoadCompleted",
    "Properties": {
      "GenericPropertyOptions": [
        {
          "CosmeticProperties": [
            {
              "AssembledMeshSchema": {
                "AssetPathName": "",
                "SubPathString": ""
              },
              "PropertyTag": {
                "TagName": "Cosmetics.Variant.Property.FigureDetailsLevel"
              }
            }
          ],
          "MetaTags": {
            "MetaTagsToApply": [],
            "MetaTagsToRemove": []
          },
          "bStartUnlocked": true,
          "bIsDefault": true,
          "bHideIfNotOwned": false,
          "CustomizationVariantTag": {
            "TagName": "Cosmetics.Variant.Property.FigureDetailsLevel.Signature"
          },
          "VariantName": {
            "Namespace": "JunoAccountItemsConversionTypes",
            "Key": "FigureDetailsLevelSignature",
            "SourceString": "Signature",
            "LocalizedString": "Signature"
          },
          "PreviewImage": {
            "AssetPathName": "",
            "SubPathString": ""
          },
          "UnlockRequirements": {
            "CultureInvariantString": null
          },
          "UnlockingItemDef": {
            "AssetPathName": "",
            "SubPathString": ""
          },
          "VariantGameplayTags": []
        },
        {
          "CosmeticProperties": [
            {
              "AssembledMeshSchema": {
                "AssetPathName": "",
                "SubPathString": ""
              },
              "PropertyTag": {
                "TagName": "Cosmetics.Variant.Property.FigureDetailsLevel"
              }
            }
          ],
          "MetaTags": {
            "MetaTagsToApply": [],
            "MetaTagsToRemove": []
          },
          "bStartUnlocked": true,
          "bIsDefault": false,
          "bHideIfNotOwned": false,
          "CustomizationVariantTag": {
            "TagName": "Cosmetics.Variant.Property.FigureDetailsLevel.Simple"
          },
          "VariantName": {
            "Namespace": "JunoAccountItemsConversionTypes",
            "Key": "FigureDetailsLevelSimple",
            "SourceString": "Base",
            "LocalizedString": "Base"
          },
          "PreviewImage": {
            "AssetPathName": "",
            "SubPathString": ""
          },
          "UnlockRequirements": {
            "CultureInvariantString": null
          },
          "UnlockingItemDef": {
            "AssetPathName": "",
            "SubPathString": ""
          },
          "VariantGameplayTags": []
        }
      ],
      "VariantChannelName": {
        "Namespace": "JunoAccountItemsConversionTypes",
        "Key": "FigureDetailsLevelChannelName",
        "SourceString": "LEGO® Style",
        "LocalizedString": "LEGO® Style"
      },
      "ProductTags": [
        {
          "TagName": "Product.Juno"
        }
      ],
      "VariantChannelTag": {
        "TagName": "Cosmetics.Variant.Channel.FigureDetailsLevel"
      }
    }
  }
]