[
  {
    "Type": "AthenaCharacterItemDefinition",
    "Name": "CID_A_178_Athena_Commando_F_TieDyeFashion_C",
    "Class": "UScriptClass'AthenaCharacterItemDefinition'",
    "Flags": "RF_Public | RF_Standalone | RF_Transactional | RF_WasLoaded | RF_LoadCompleted",
    "Properties": {
      "BaseCharacterParts": [
        {
          "AssetPathName": "/BRCosmetics/Characters/CharacterParts/Female/Medium/Heads/CP_Athena_Head_F_TieDyeFashion_C.CP_Athena_Head_F_TieDyeFashion_C",
          "SubPathString": ""
        },
        {
          "AssetPathName": "/BRCosmetics/Athena/Heroes/Meshes/Bodies/CP_Athena_Body_F_TieDyeFashion.CP_Athena_Body_F_TieDyeFashion",
          "SubPathString": ""
        },
        {
          "AssetPathName": "/BRCosmetics/Characters/CharacterParts/FaceAccessories/CP_F_MED_TieDyeFashion_C.CP_F_MED_TieDyeFashion_C",
          "SubPathString": ""
        }
      ],
      "Gender": "EFortCustomGender::Female",
      "DefaultMontageLookupTable": {
        "AssetPathName": "/Game/Animation/Game/MainPlayer/Menu/MontageLookUpTables/MediumFemale.MediumFemale",
        "SubPathString": ""
      },
      "ItemVariants": [
        {
          "ObjectName": "FortCosmeticMaterialVariant'CID_A_178_Athena_Commando_F_TieDyeFashion_C:FortCosmeticMaterialVariant_0'",
          "ObjectPath": "/BRCosmetics/Athena/Items/Cosmetics/Characters/CID_A_178_Athena_Commando_F_TieDyeFashion_C.1"
        },
        {
          "ObjectName": "FortCosmeticRichColorVariant'CID_A_178_Athena_Commando_F_TieDyeFashion_C:FortCosmeticRichColorVariant_1'",
          "ObjectPath": "/BRCosmetics/Athena/Items/Cosmetics/Characters/CID_A_178_Athena_Commando_F_TieDyeFashion_C.4"
        },
        {
          "ObjectName": "FortCosmeticRichColorVariant'CID_A_178_Athena_Commando_F_TieDyeFashion_C:FortCosmeticRichColorVariant_2'",
          "ObjectPath": "/BRCosmetics/Athena/Items/Cosmetics/Characters/CID_A_178_Athena_Commando_F_TieDyeFashion_C.5"
        },
        {
          "ObjectName": "FortCosmeticRichColorVariant'CID_A_178_Athena_Commando_F_TieDyeFashion_C:FortCosmeticRichColorVariant_0'",
          "ObjectPath": "/BRCosmetics/Athena/Items/Cosmetics/Characters/CID_A_178_Athena_Commando_F_TieDyeFashion_C.3"
        },
        {
          "ObjectName": "FortCosmeticPropertyVariant'CID_A_178_Athena_Commando_F_TieDyeFashion_C:FortCosmeticPropertyVariant_0'",
          "ObjectPath": "/BRCosmetics/Athena/Items/Cosmetics/Characters/CID_A_178_Athena_Commando_F_TieDyeFashion_C.2"
        }
      ],
      "BaseShotGridId": 40230,
      "ShotGridIds": [
        40230
      ],
      "ItemName": {
        "Namespace": "",
        "Key": "021E42A44998A68F39B076B5C0D94041",
        "SourceString": "Swirl Girl",
        "LocalizedString": "Swirl Girl"
      },
      "ItemDescription": {
        "Namespace": "",
        "Key": "FF8E07B1493C26F23931099845875CE6",
        "SourceString": "Dress code is \"Victory Casuale.\"",
        "LocalizedString": "Dress code is \"Victory Casuale.\""
      },
      "ItemShortDescription": {
        "Namespace": "",
        "Key": "9658361F4EFF6B98FF153898E58C9D52",
        "SourceString": "Outfit",
        "LocalizedString": "Outfit"
      },
      "DataList": [
        {
          "LargeIcon": {
            "AssetPathName": "/BRCosmetics/UI/Foundation/Textures/Icons/Heroes/Athena/Soldier/T-Soldier-HID-A-178-Athena-Commando-F-TieDyeFashion-C-L.T-Soldier-HID-A-178-Athena-Commando-F-TieDyeFashion-C-L",
            "SubPathString": ""
          }
        },
        {
          "Icon": {
            "AssetPathName": "/BRCosmetics/UI/Foundation/Textures/Icons/Heroes/Athena/Soldier/T-Soldier-HID-A-178-Athena-Commando-F-TieDyeFashion-C.T-Soldier-HID-A-178-Athena-Commando-F-TieDyeFashion-C",
            "SubPathString": ""
          }
        },
        {
          "MinLevel": 1,
          "MaxLevel": 1
        },
        {
          "Tags": [
            "Cosmetics.Source.ItemShop",
            "Cosmetics.Filter.Season.17",
            "Cosmetics.UserFacingFlags.HasVariants",
            "Cosmetics.Set.GoingWayOff",
            "Phoebe.Cosmetic.Minus.Zone1",
            "Phoebe.Cosmetic.Minus.Zone2",
            "SoundLibrary.ID.StepType.ShoesSneakers",
            "SoundLibrary.ID.ClothingType.Generic",
            "SoundLibrary.ID.HandType.Bare",
            "Cosmetics.FrontEndPose.DontHandsOnHips",
            "Cosmetics.Gating.Allow.Shoes"
          ]
        },
        {
          "Traits": [
            "Item.Trait.SingleStack"
          ]
        },
        {
          "GeneratedTagsIndexes": [
            543,
            549,
            7,
            7975,
            12,
            541,
            236,
            544,
            242,
            172,
            243,
            269,
            54,
            244,
            684,
            682,
            706,
            705,
            711,
            707,
            703,
            708,
            712,
            41,
            275,
            722,
            726,
            789,
            152,
            808,
            809,
            775,
            927,
            924,
            1180,
            1183,
            1332,
            1412
          ]
        }
      ]
    }
  },
  {
    "Type": "FortCosmeticMaterialVariant",
    "Name": "FortCosmeticMaterialVariant_0",
    "Outer": "CID_A_178_Athena_Commando_F_TieDyeFashion_C",
    "Class": "UScriptClass'FortCosmeticMaterialVariant'",
    "Flags": "RF_Public | RF_Transactional | RF_WasLoaded | RF_LoadCompleted",
    "Properties": {
      "MaterialOptions": [
        {
          "VariantMaterials": [
            {
              "MaterialToSwap": {
                "AssetPathName": "/Game/Characters/Player/Female/Medium/Bodies/F_MED_Tie_Dye_Fashion/Materials/M_F_Tie_Dye_Fashion_Body.M_F_Tie_Dye_Fashion_Body",
                "SubPathString": ""
              },
              "ComponentToOverride": "None",
              "CascadeMaterialName": "None",
              "MaterialOverrideIndex": 0,
              "OverrideMaterial": {
                "AssetPathName": "/BRCosmetics/Characters/Player/Female/Medium/Bodies/F_MED_Tie_Dye_Fashion/Materials/M_F_Tie_Dye_Fashion_Body_V.M_F_Tie_Dye_Fashion_Body_V",
                "SubPathString": ""
              }
            }
          ],
          "VariantMaterialParams": [],
          "VariantSounds": [],
          "VariantFoley": [],
          "CosmeticProperties": [],
          "MetaTags": {
            "MetaTagsToApply": [],
            "MetaTagsToRemove": []
          },
          "bStartUnlocked": true,
          "bIsDefault": true,
          "bHideIfNotOwned": false,
          "CustomizationVariantTag": {
            "TagName": "Cosmetics.Variant.Property.Mat2"
          },
          "VariantName": {
            "Namespace": "",
            "Key": "AD4AD8EE4C8A84F22EB55A9CE869B9BD",
            "SourceString": "V",
            "LocalizedString": "V"
          },
          "PreviewImage": {
            "AssetPathName": "/BRCosmetics/UI/Foundation/Textures/Icons/Heroes/Variants/TieDyeFashion/T_UI_TieDyeFashion_DyePattern_V.T_UI_TieDyeFashion_DyePattern_V",
            "SubPathString": ""
          },
          "UnlockRequirements": {
            "CultureInvariantString": null
          },
          "UnlockingItemDef": {
            "AssetPathName": "",
            "SubPathString": ""
          },
          "VariantGameplayTags": []
        },
        {
          "VariantMaterials": [
            {
              "MaterialToSwap": {
                "AssetPathName": "/Game/Characters/Player/Female/Medium/Bodies/F_MED_Tie_Dye_Fashion/Materials/M_F_Tie_Dye_Fashion_Body.M_F_Tie_Dye_Fashion_Body",
                "SubPathString": ""
              },
              "ComponentToOverride": "None",
              "CascadeMaterialName": "None",
              "MaterialOverrideIndex": 0,
              "OverrideMaterial": {
                "AssetPathName": "/BRCosmetics/Characters/Player/Female/Medium/Bodies/F_MED_Tie_Dye_Fashion/Materials/M_F_Tie_Dye_Fashion_Body_Cloud.M_F_Tie_Dye_Fashion_Body_Cloud",
                "SubPathString": ""
              }
            }
          ],
          "VariantMaterialParams": [],
          "VariantSounds": [],
          "VariantFoley": [],
          "CosmeticProperties": [],
          "MetaTags": {
            "MetaTagsToApply": [],
            "MetaTagsToRemove": []
          },
          "bStartUnlocked": true,
          "bIsDefault": false,
          "bHideIfNotOwned": false,
          "CustomizationVariantTag": {
            "TagName": "Cosmetics.Variant.Property.Mat1"
          },
          "VariantName": {
            "Namespace": "",
            "Key": "1BFB95BC420E58E4A5831084FF795F9B",
            "SourceString": "cloud",
            "LocalizedString": "cloud"
          },
          "PreviewImage": {
            "AssetPathName": "/BRCosmetics/UI/Foundation/Textures/Icons/Heroes/Variants/TieDyeFashion/T_UI_TieDyeFashion_DyePattern_Cloud.T_UI_TieDyeFashion_DyePattern_Cloud",
            "SubPathString": ""
          },
          "UnlockRequirements": {
            "CultureInvariantString": null
          },
          "UnlockingItemDef": {
            "AssetPathName": "",
            "SubPathString": ""
          },
          "VariantGameplayTags": []
        },
        {
          "VariantMaterials": [
            {
              "MaterialToSwap": {
                "AssetPathName": "/Game/Characters/Player/Female/Medium/Bodies/F_MED_Tie_Dye_Fashion/Materials/M_F_Tie_Dye_Fashion_Body.M_F_Tie_Dye_Fashion_Body",
                "SubPathString": ""
              },
              "ComponentToOverride": "None",
              "CascadeMaterialName": "None",
              "MaterialOverrideIndex": 0,
              "OverrideMaterial": {
                "AssetPathName": "/BRCosmetics/Characters/Player/Female/Medium/Bodies/F_MED_Tie_Dye_Fashion/Materials/M_F_Tie_Dye_Fashion_Body_Grid.M_F_Tie_Dye_Fashion_Body_Grid",
                "SubPathString": ""
              }
            }
          ],
          "VariantMaterialParams": [],
          "VariantSounds": [],
          "VariantFoley": [],
          "CosmeticProperties": [],
          "MetaTags": {
            "MetaTagsToApply": [],
            "MetaTagsToRemove": []
          },
          "bStartUnlocked": true,
          "bIsDefault": false,
          "bHideIfNotOwned": false,
          "CustomizationVariantTag": {
            "TagName": "Cosmetics.Variant.Property.Mat3"
          },
          "VariantName": {
            "Namespace": "",
            "Key": "21388185404B675DDF70A4819B07BC51",
            "SourceString": "grid",
            "LocalizedString": "grid"
          },
          "PreviewImage": {
            "AssetPathName": "/BRCosmetics/UI/Foundation/Textures/Icons/Heroes/Variants/TieDyeFashion/T_UI_TieDyeFashion_DyePattern_Grid.T_UI_TieDyeFashion_DyePattern_Grid",
            "SubPathString": ""
          },
          "UnlockRequirements": {
            "CultureInvariantString": null
          },
          "UnlockingItemDef": {
            "AssetPathName": "",
            "SubPathString": ""
          },
          "VariantGameplayTags": []
        },
        {
          "VariantMaterials": [
            {
              "MaterialToSwap": {
                "AssetPathName": "/Game/Characters/Player/Female/Medium/Bodies/F_MED_Tie_Dye_Fashion/Materials/M_F_Tie_Dye_Fashion_Body.M_F_Tie_Dye_Fashion_Body",
                "SubPathString": ""
              },
              "ComponentToOverride": "None",
              "CascadeMaterialName": "None",
              "MaterialOverrideIndex": 0,
              "OverrideMaterial": {
                "AssetPathName": "/BRCosmetics/Characters/Player/Female/Medium/Bodies/F_MED_Tie_Dye_Fashion/Materials/M_F_Tie_Dye_Fashion_Body_BullsEye.M_F_Tie_Dye_Fashion_Body_BullsEye",
                "SubPathString": ""
              }
            }
          ],
          "VariantMaterialParams": [],
          "VariantSounds": [],
          "VariantFoley": [],
          "CosmeticProperties": [],
          "MetaTags": {
            "MetaTagsToApply": [],
            "MetaTagsToRemove": []
          },
          "bStartUnlocked": true,
          "bIsDefault": false,
          "bHideIfNotOwned": false,
          "CustomizationVariantTag": {
            "TagName": "Cosmetics.Variant.Property.Mat4"
          },
          "VariantName": {
            "Namespace": "",
            "Key": "0241AE75472677DC2192458961408C50",
            "SourceString": "bullseye",
            "LocalizedString": "bullseye"
          },
          "PreviewImage": {
            "AssetPathName": "/BRCosmetics/UI/Foundation/Textures/Icons/Heroes/Variants/TieDyeFashion/T_UI_TieDyeFashion_DyePattern_Bullseye.T_UI_TieDyeFashion_DyePattern_Bullseye",
            "SubPathString": ""
          },
          "UnlockRequirements": {
            "CultureInvariantString": null
          },
          "UnlockingItemDef": {
            "AssetPathName": "",
            "SubPathString": ""
          },
          "VariantGameplayTags": []
        },
        {
          "VariantMaterials": [
            {
              "MaterialToSwap": {
                "AssetPathName": "/Game/Characters/Player/Female/Medium/Bodies/F_MED_Tie_Dye_Fashion/Materials/M_F_Tie_Dye_Fashion_Body.M_F_Tie_Dye_Fashion_Body",
                "SubPathString": ""
              },
              "ComponentToOverride": "None",
              "CascadeMaterialName": "None",
              "MaterialOverrideIndex": 0,
              "OverrideMaterial": {
                "AssetPathName": "/BRCosmetics/Characters/Player/Female/Medium/Bodies/F_MED_Tie_Dye_Fashion/Materials/M_F_Tie_Dye_Fashion_Body_Ombre.M_F_Tie_Dye_Fashion_Body_Ombre",
                "SubPathString": ""
              }
            }
          ],
          "VariantMaterialParams": [],
          "VariantSounds": [],
          "VariantFoley": [],
          "CosmeticProperties": [],
          "MetaTags": {
            "MetaTagsToApply": [],
            "MetaTagsToRemove": []
          },
          "bStartUnlocked": true,
          "bIsDefault": false,
          "bHideIfNotOwned": false,
          "CustomizationVariantTag": {
            "TagName": "Cosmetics.Variant.Property.Mat5"
          },
          "VariantName": {
            "Namespace": "",
            "Key": "32BCF690466913E9C2CAABA34A35408A",
            "SourceString": "ombre",
            "LocalizedString": "ombre"
          },
          "PreviewImage": {
            "AssetPathName": "/BRCosmetics/UI/Foundation/Textures/Icons/Heroes/Variants/TieDyeFashion/T_UI_TieDyeFashion_DyePattern_Ombre.T_UI_TieDyeFashion_DyePattern_Ombre",
            "SubPathString": ""
          },
          "UnlockRequirements": {
            "CultureInvariantString": null
          },
          "UnlockingItemDef": {
            "AssetPathName": "",
            "SubPathString": ""
          },
          "VariantGameplayTags": []
        },
        {
          "VariantMaterials": [
            {
              "MaterialToSwap": {
                "AssetPathName": "/Game/Characters/Player/Female/Medium/Bodies/F_MED_Tie_Dye_Fashion/Materials/M_F_Tie_Dye_Fashion_Body.M_F_Tie_Dye_Fashion_Body",
                "SubPathString": ""
              },
              "ComponentToOverride": "None",
              "CascadeMaterialName": "None",
              "MaterialOverrideIndex": 0,
              "OverrideMaterial": {
                "AssetPathName": "/BRCosmetics/Characters/Player/Female/Medium/Bodies/F_MED_Tie_Dye_Fashion/Materials/M_F_Tie_Dye_Fashion_Body_Spiral.M_F_Tie_Dye_Fashion_Body_Spiral",
                "SubPathString": ""
              }
            }
          ],
          "VariantMaterialParams": [],
          "VariantSounds": [],
          "VariantFoley": [],
          "CosmeticProperties": [],
          "MetaTags": {
            "MetaTagsToApply": [],
            "MetaTagsToRemove": []
          },
          "bStartUnlocked": true,
          "bIsDefault": false,
          "bHideIfNotOwned": false,
          "CustomizationVariantTag": {
            "TagName": "Cosmetics.Variant.Property.Mat6"
          },
          "VariantName": {
            "Namespace": "",
            "Key": "A6CF515F459A04B58B12A99FF21644AD",
            "SourceString": "spiral",
            "LocalizedString": "spiral"
          },
          "PreviewImage": {
            "AssetPathName": "/BRCosmetics/UI/Foundation/Textures/Icons/Heroes/Variants/TieDyeFashion/T_UI_TieDyeFashion_DyePattern_Spiral.T_UI_TieDyeFashion_DyePattern_Spiral",
            "SubPathString": ""
          },
          "UnlockRequirements": {
            "CultureInvariantString": null
          },
          "UnlockingItemDef": {
            "AssetPathName": "",
            "SubPathString": ""
          },
          "VariantGameplayTags": []
        },
        {
          "VariantMaterials": [
            {
              "MaterialToSwap": {
                "AssetPathName": "/Game/Characters/Player/Female/Medium/Bodies/F_MED_Tie_Dye_Fashion/Materials/M_F_Tie_Dye_Fashion_Body.M_F_Tie_Dye_Fashion_Body",
                "SubPathString": ""
              },
              "ComponentToOverride": "None",
              "CascadeMaterialName": "None",
              "MaterialOverrideIndex": 0,
              "OverrideMaterial": {
                "AssetPathName": "/Game/Characters/Player/Female/Medium/Bodies/F_MED_Tie_Dye_Fashion/Skins/F_MED_Tie_Dye_Fashion_Summer/Material/M_F_Tie_Dye_Fashion_Summer_Lime.M_F_Tie_Dye_Fashion_Summer_Lime",
                "SubPathString": ""
              }
            }
          ],
          "VariantMaterialParams": [],
          "VariantSounds": [],
          "VariantFoley": [],
          "CosmeticProperties": [],
          "MetaTags": {
            "MetaTagsToApply": [],
            "MetaTagsToRemove": []
          },
          "bStartUnlocked": true,
          "bIsDefault": false,
          "bHideIfNotOwned": false,
          "CustomizationVariantTag": {
            "TagName": "Cosmetics.Variant.Property.Mat7"
          },
          "VariantName": {
            "Namespace": "",
            "Key": "71ABE9A94CA2CF744D524B82722FE63B",
            "SourceString": "Lime",
            "LocalizedString": "Lime"
          },
          "PreviewImage": {
            "AssetPathName": "/BRCosmetics/UI/Foundation/Textures/Icons/Heroes/Variants/TieDyeFashion/T_UI_TieDyeFashion_DyePattern_Lime.T_UI_TieDyeFashion_DyePattern_Lime",
            "SubPathString": ""
          },
          "UnlockRequirements": {
            "CultureInvariantString": null
          },
          "UnlockingItemDef": {
            "AssetPathName": "",
            "SubPathString": ""
          },
          "VariantGameplayTags": []
        },
        {
          "VariantMaterials": [
            {
              "MaterialToSwap": {
                "AssetPathName": "/Game/Characters/Player/Female/Medium/Bodies/F_MED_Tie_Dye_Fashion/Materials/M_F_Tie_Dye_Fashion_Body.M_F_Tie_Dye_Fashion_Body",
                "SubPathString": ""
              },
              "ComponentToOverride": "None",
              "CascadeMaterialName": "None",
              "MaterialOverrideIndex": 0,
              "OverrideMaterial": {
                "AssetPathName": "/Game/Characters/Player/Female/Medium/Bodies/F_MED_Tie_Dye_Fashion/Skins/F_MED_Tie_Dye_Fashion_Summer/Material/M_F_Tie_Dye_Fashion_Summer_Cloud.M_F_Tie_Dye_Fashion_Summer_Cloud",
                "SubPathString": ""
              }
            }
          ],
          "VariantMaterialParams": [],
          "VariantSounds": [],
          "VariantFoley": [],
          "CosmeticProperties": [],
          "MetaTags": {
            "MetaTagsToApply": [],
            "MetaTagsToRemove": []
          },
          "bStartUnlocked": true,
          "bIsDefault": false,
          "bHideIfNotOwned": false,
          "CustomizationVariantTag": {
            "TagName": "Cosmetics.Variant.Property.Mat8"
          },
          "VariantName": {
            "Namespace": "",
            "Key": "5ACC3FAF40F34FC8AF455E9A1AC1D1D0",
            "SourceString": "Summer Cloud",
            "LocalizedString": "Summer Cloud"
          },
          "PreviewImage": {
            "AssetPathName": "/BRCosmetics/UI/Foundation/Textures/Icons/Heroes/Variants/TieDyeFashion/T_UI_TieDyeFashion_DyePattern_SummerCloud.T_UI_TieDyeFashion_DyePattern_SummerCloud",
            "SubPathString": ""
          },
          "UnlockRequirements": {
            "CultureInvariantString": null
          },
          "UnlockingItemDef": {
            "AssetPathName": "",
            "SubPathString": ""
          },
          "VariantGameplayTags": []
        },
        {
          "VariantMaterials": [
            {
              "MaterialToSwap": {
                "AssetPathName": "/Game/Characters/Player/Female/Medium/Bodies/F_MED_Tie_Dye_Fashion/Materials/M_F_Tie_Dye_Fashion_Body.M_F_Tie_Dye_Fashion_Body",
                "SubPathString": ""
              },
              "ComponentToOverride": "None",
              "CascadeMaterialName": "None",
              "MaterialOverrideIndex": 0,
              "OverrideMaterial": {
                "AssetPathName": "/Game/Characters/Player/Female/Medium/Bodies/F_MED_Tie_Dye_Fashion/Skins/F_MED_Tie_Dye_Fashion_Summer/Material/M_F_Tie_Dye_Fashion_Summer_Zebra.M_F_Tie_Dye_Fashion_Summer_Zebra",
                "SubPathString": ""
              }
            }
          ],
          "VariantMaterialParams": [],
          "VariantSounds": [],
          "VariantFoley": [],
          "CosmeticProperties": [],
          "MetaTags": {
            "MetaTagsToApply": [],
            "MetaTagsToRemove": []
          },
          "bStartUnlocked": true,
          "bIsDefault": false,
          "bHideIfNotOwned": false,
          "CustomizationVariantTag": {
            "TagName": "Cosmetics.Variant.Property.Mat9"
          },
          "VariantName": {
            "Namespace": "",
            "Key": "6E277E154223F8D7BF64FD8D27B0735B",
            "SourceString": "Zebra",
            "LocalizedString": "Zebra"
          },
          "PreviewImage": {
            "AssetPathName": "/BRCosmetics/UI/Foundation/Textures/Icons/Heroes/Variants/TieDyeFashion/T_UI_TieDyeFashion_DyePattern_Zebra.T_UI_TieDyeFashion_DyePattern_Zebra",
            "SubPathString": ""
          },
          "UnlockRequirements": {
            "CultureInvariantString": null
          },
          "UnlockingItemDef": {
            "AssetPathName": "",
            "SubPathString": ""
          },
          "VariantGameplayTags": []
        }
      ],
      "VariantChannelName": {
        "Namespace": "",
        "Key": "B21983DB4B1CEDBF0203DAAF8999E120",
        "SourceString": "Pattern",
        "LocalizedString": "Pattern"
      },
      "VariantChannelTag": {
        "TagName": "Cosmetics.Variant.Channel.Material"
      }
    }
  },
  {
    "Type": "FortCosmeticPropertyVariant",
    "Name": "FortCosmeticPropertyVariant_0",
    "Outer": "CID_A_178_Athena_Commando_F_TieDyeFashion_C",
    "Class": "UScriptClass'FortCosmeticPropertyVariant'",
    "Flags": "RF_WasLoaded | RF_LoadCompleted",
    "Properties": {
      "GenericPropertyOptions": [
        {
          "CosmeticProperties": [
            {
              "AssembledMeshSchema": {
                "AssetPathName": "",
                "SubPathString": ""
              },
              "PropertyTag": {
                "TagName": "Cosmetics.Variant.Property.FigureDetailsLevel"
              }
            }
          ],
          "MetaTags": {
            "MetaTagsToApply": [],
            "MetaTagsToRemove": []
          },
          "bStartUnlocked": true,
          "bIsDefault": true,
          "bHideIfNotOwned": false,
          "CustomizationVariantTag": {
            "TagName": "Cosmetics.Variant.Property.FigureDetailsLevel.Signature"
          },
          "VariantName": {
            "Namespace": "JunoAccountItemsConversionTypes",
            "Key": "FigureDetailsLevelSignature",
            "SourceString": "Signature",
            "LocalizedString": "Signature"
          },
          "PreviewImage": {
            "AssetPathName": "",
            "SubPathString": ""
          },
          "UnlockRequirements": {
            "CultureInvariantString": null
          },
          "UnlockingItemDef": {
            "AssetPathName": "",
            "SubPathString": ""
          },
          "VariantGameplayTags": []
        },
        {
          "CosmeticProperties": [
            {
              "AssembledMeshSchema": {
                "AssetPathName": "",
                "SubPathString": ""
              },
              "PropertyTag": {
                "TagName": "Cosmetics.Variant.Property.FigureDetailsLevel"
              }
            }
          ],
          "MetaTags": {
            "MetaTagsToApply": [],
            "MetaTagsToRemove": []
          },
          "bStartUnlocked": true,
          "bIsDefault": false,
          "bHideIfNotOwned": false,
          "CustomizationVariantTag": {
            "TagName": "Cosmetics.Variant.Property.FigureDetailsLevel.Simple"
          },
          "VariantName": {
            "Namespace": "JunoAccountItemsConversionTypes",
            "Key": "FigureDetailsLevelSimple",
            "SourceString": "Base",
            "LocalizedString": "Base"
          },
          "PreviewImage": {
            "AssetPathName": "",
            "SubPathString": ""
          },
          "UnlockRequirements": {
            "CultureInvariantString": null
          },
          "UnlockingItemDef": {
            "AssetPathName": "",
            "SubPathString": ""
          },
          "VariantGameplayTags": []
        }
      ],
      "VariantChannelName": {
        "Namespace": "JunoAccountItemsConversionTypes",
        "Key": "FigureDetailsLevelChannelName",
        "SourceString": "LEGO® Style",
        "LocalizedString": "LEGO® Style"
      },
      "ProductTags": [
        {
          "TagName": "Product.Juno"
        }
      ],
      "VariantChannelTag": {
        "TagName": "Cosmetics.Variant.Channel.FigureDetailsLevel"
      }
    }
  },
  {
    "Type": "FortCosmeticRichColorVariant",
    "Name": "FortCosmeticRichColorVariant_0",
    "Outer": "CID_A_178_Athena_Commando_F_TieDyeFashion_C",
    "Class": "UScriptClass'FortCosmeticRichColorVariant'",
    "Flags": "RF_Public | RF_Transactional | RF_WasLoaded | RF_LoadCompleted",
    "Properties": {
      "InlineVariant": {
        "RichColorVar": {
          "DefaultStartingColor": {
            "R": 0.064803,
            "G": 0.630757,
            "B": 0.603827,
            "A": 1.0,
            "Hex": "48D0CC"
          },
          "ColorSwatchForChoices": {
            "AssetPathName": "/Game/Characters/CharacterColorSwatches/Misc/CS_TieDyeFashion_Expanded.CS_TieDyeFashion_Expanded",
            "SubPathString": ""
          },
          "MaterialsToAlter": [
            {
              "AssetPathName": "/Game/Characters/Player/Female/Medium/Bodies/F_MED_Tie_Dye_Fashion/Materials/M_F_Tie_Dye_Fashion_Body.M_F_Tie_Dye_Fashion_Body",
              "SubPathString": ""
            },
            {
              "AssetPathName": "/BRCosmetics/Characters/Player/Female/Medium/Bodies/F_MED_Tie_Dye_Fashion/Materials/M_F_Tie_Dye_Fashion_Body_Spiral.M_F_Tie_Dye_Fashion_Body_Spiral",
              "SubPathString": ""
            },
            {
              "AssetPathName": "/BRCosmetics/Characters/Player/Female/Medium/Bodies/F_MED_Tie_Dye_Fashion/Materials/M_F_Tie_Dye_Fashion_Body_Ombre.M_F_Tie_Dye_Fashion_Body_Ombre",
              "SubPathString": ""
            },
            {
              "AssetPathName": "/BRCosmetics/Characters/Player/Female/Medium/Bodies/F_MED_Tie_Dye_Fashion/Materials/M_F_Tie_Dye_Fashion_Body_V.M_F_Tie_Dye_Fashion_Body_V",
              "SubPathString": ""
            },
            {
              "AssetPathName": "/BRCosmetics/Characters/Player/Female/Medium/Bodies/F_MED_Tie_Dye_Fashion/Materials/M_F_Tie_Dye_Fashion_Body_Cloud.M_F_Tie_Dye_Fashion_Body_Cloud",
              "SubPathString": ""
            },
            {
              "AssetPathName": "/BRCosmetics/Characters/Player/Female/Medium/Bodies/F_MED_Tie_Dye_Fashion/Materials/M_F_Tie_Dye_Fashion_Body_Grid.M_F_Tie_Dye_Fashion_Body_Grid",
              "SubPathString": ""
            },
            {
              "AssetPathName": "/BRCosmetics/Characters/Player/Female/Medium/Bodies/F_MED_Tie_Dye_Fashion/Materials/M_F_Tie_Dye_Fashion_Body_BullsEye.M_F_Tie_Dye_Fashion_Body_BullsEye",
              "SubPathString": ""
            },
            {
              "AssetPathName": "/Game/Characters/Player/Female/Medium/Bodies/F_MED_Tie_Dye_Fashion/Skins/F_MED_Tie_Dye_Fashion_Summer/Material/M_F_Tie_Dye_Fashion_Summer_Cloud.M_F_Tie_Dye_Fashion_Summer_Cloud",
              "SubPathString": ""
            },
            {
              "AssetPathName": "/Game/Characters/Player/Female/Medium/Bodies/F_MED_Tie_Dye_Fashion/Skins/F_MED_Tie_Dye_Fashion_Summer/Material/M_F_Tie_Dye_Fashion_Summer_Lime.M_F_Tie_Dye_Fashion_Summer_Lime",
              "SubPathString": ""
            },
            {
              "AssetPathName": "/Game/Characters/Player/Female/Medium/Bodies/F_MED_Tie_Dye_Fashion/Skins/F_MED_Tie_Dye_Fashion_Summer/Material/M_F_Tie_Dye_Fashion_Summer_Zebra.M_F_Tie_Dye_Fashion_Summer_Zebra",
              "SubPathString": ""
            }
          ],
          "ColorParamName": "TieDye_Color_3"
        }
      },
      "VariantChannelName": {
        "Namespace": "",
        "Key": "5F9B81ED4D8BFF7EA5467F850535999D",
        "SourceString": "Color 3",
        "LocalizedString": "Color 3"
      },
      "VariantChannelTag": {
        "TagName": "Cosmetics.Variant.Channel.RichColor3"
      }
    }
  },
  {
    "Type": "FortCosmeticRichColorVariant",
    "Name": "FortCosmeticRichColorVariant_1",
    "Outer": "CID_A_178_Athena_Commando_F_TieDyeFashion_C",
    "Class": "UScriptClass'FortCosmeticRichColorVariant'",
    "Flags": "RF_Public | RF_Transactional | RF_WasLoaded | RF_LoadCompleted",
    "Properties": {
      "InlineVariant": {
        "RichColorVar": {
          "DefaultStartingColor": {
            "R": 0.879622,
            "G": 0.309469,
            "B": 0.006512,
            "A": 1.0,
            "Hex": "F19713"
          },
          "ColorSwatchForChoices": {
            "AssetPathName": "/Game/Characters/CharacterColorSwatches/Misc/CS_TieDyeFashion_Expanded.CS_TieDyeFashion_Expanded",
            "SubPathString": ""
          },
          "MaterialsToAlter": [
            {
              "AssetPathName": "/Game/Characters/Player/Female/Medium/Bodies/F_MED_Tie_Dye_Fashion/Materials/M_F_Tie_Dye_Fashion_Body.M_F_Tie_Dye_Fashion_Body",
              "SubPathString": ""
            },
            {
              "AssetPathName": "/BRCosmetics/Characters/Player/Female/Medium/Bodies/F_MED_Tie_Dye_Fashion/Materials/M_F_Tie_Dye_Fashion_Body_Spiral.M_F_Tie_Dye_Fashion_Body_Spiral",
              "SubPathString": ""
            },
            {
              "AssetPathName": "/BRCosmetics/Characters/Player/Female/Medium/Bodies/F_MED_Tie_Dye_Fashion/Materials/M_F_Tie_Dye_Fashion_Body_Ombre.M_F_Tie_Dye_Fashion_Body_Ombre",
              "SubPathString": ""
            },
            {
              "AssetPathName": "/BRCosmetics/Characters/Player/Female/Medium/Bodies/F_MED_Tie_Dye_Fashion/Materials/M_F_Tie_Dye_Fashion_Body_V.M_F_Tie_Dye_Fashion_Body_V",
              "SubPathString": ""
            },
            {
              "AssetPathName": "/BRCosmetics/Characters/Player/Female/Medium/Bodies/F_MED_Tie_Dye_Fashion/Materials/M_F_Tie_Dye_Fashion_Body_Cloud.M_F_Tie_Dye_Fashion_Body_Cloud",
              "SubPathString": ""
            },
            {
              "AssetPathName": "/BRCosmetics/Characters/Player/Female/Medium/Bodies/F_MED_Tie_Dye_Fashion/Materials/M_F_Tie_Dye_Fashion_Body_Grid.M_F_Tie_Dye_Fashion_Body_Grid",
              "SubPathString": ""
            },
            {
              "AssetPathName": "/BRCosmetics/Characters/Player/Female/Medium/Bodies/F_MED_Tie_Dye_Fashion/Materials/M_F_Tie_Dye_Fashion_Body_BullsEye.M_F_Tie_Dye_Fashion_Body_BullsEye",
              "SubPathString": ""
            },
            {
              "AssetPathName": "/Game/Characters/Player/Female/Medium/Bodies/F_MED_Tie_Dye_Fashion/Skins/F_MED_Tie_Dye_Fashion_Summer/Material/M_F_Tie_Dye_Fashion_Summer_Cloud.M_F_Tie_Dye_Fashion_Summer_Cloud",
              "SubPathString": ""
            },
            {
              "AssetPathName": "/Game/Characters/Player/Female/Medium/Bodies/F_MED_Tie_Dye_Fashion/Skins/F_MED_Tie_Dye_Fashion_Summer/Material/M_F_Tie_Dye_Fashion_Summer_Lime.M_F_Tie_Dye_Fashion_Summer_Lime",
              "SubPathString": ""
            },
            {
              "AssetPathName": "/Game/Characters/Player/Female/Medium/Bodies/F_MED_Tie_Dye_Fashion/Skins/F_MED_Tie_Dye_Fashion_Summer/Material/M_F_Tie_Dye_Fashion_Summer_Zebra.M_F_Tie_Dye_Fashion_Summer_Zebra",
              "SubPathString": ""
            }
          ],
          "ColorParamName": "TieDye_Color_1"
        }
      },
      "VariantChannelName": {
        "Namespace": "",
        "Key": "71F9BE2448BD06ADF4787986F1CA08BB",
        "SourceString": "Color 1",
        "LocalizedString": "Color 1"
      }
    }
  },
  {
    "Type": "FortCosmeticRichColorVariant",
    "Name": "FortCosmeticRichColorVariant_2",
    "Outer": "CID_A_178_Athena_Commando_F_TieDyeFashion_C",
    "Class": "UScriptClass'FortCosmeticRichColorVariant'",
    "Flags": "RF_Public | RF_Transactional | RF_WasLoaded | RF_LoadCompleted",
    "Properties": {
      "InlineVariant": {
        "RichColorVar": {
          "DefaultStartingColor": {
            "R": 0.132868,
            "G": 0.046665,
            "B": 0.450786,
            "A": 1.0,
            "Hex": "663DB3"
          },
          "ColorSwatchForChoices": {
            "AssetPathName": "/Game/Characters/CharacterColorSwatches/Misc/CS_TieDyeFashion_Expanded.CS_TieDyeFashion_Expanded",
            "SubPathString": ""
          },
          "MaterialsToAlter": [
            {
              "AssetPathName": "/Game/Characters/Player/Female/Medium/Bodies/F_MED_Tie_Dye_Fashion/Materials/M_F_Tie_Dye_Fashion_Body.M_F_Tie_Dye_Fashion_Body",
              "SubPathString": ""
            },
            {
              "AssetPathName": "/BRCosmetics/Characters/Player/Female/Medium/Bodies/F_MED_Tie_Dye_Fashion/Materials/M_F_Tie_Dye_Fashion_Body_Spiral.M_F_Tie_Dye_Fashion_Body_Spiral",
              "SubPathString": ""
            },
            {
              "AssetPathName": "/BRCosmetics/Characters/Player/Female/Medium/Bodies/F_MED_Tie_Dye_Fashion/Materials/M_F_Tie_Dye_Fashion_Body_Ombre.M_F_Tie_Dye_Fashion_Body_Ombre",
              "SubPathString": ""
            },
            {
              "AssetPathName": "/BRCosmetics/Characters/Player/Female/Medium/Bodies/F_MED_Tie_Dye_Fashion/Materials/M_F_Tie_Dye_Fashion_Body_V.M_F_Tie_Dye_Fashion_Body_V",
              "SubPathString": ""
            },
            {
              "AssetPathName": "/BRCosmetics/Characters/Player/Female/Medium/Bodies/F_MED_Tie_Dye_Fashion/Materials/M_F_Tie_Dye_Fashion_Body_Cloud.M_F_Tie_Dye_Fashion_Body_Cloud",
              "SubPathString": ""
            },
            {
              "AssetPathName": "/BRCosmetics/Characters/Player/Female/Medium/Bodies/F_MED_Tie_Dye_Fashion/Materials/M_F_Tie_Dye_Fashion_Body_Grid.M_F_Tie_Dye_Fashion_Body_Grid",
              "SubPathString": ""
            },
            {
              "AssetPathName": "/BRCosmetics/Characters/Player/Female/Medium/Bodies/F_MED_Tie_Dye_Fashion/Materials/M_F_Tie_Dye_Fashion_Body_BullsEye.M_F_Tie_Dye_Fashion_Body_BullsEye",
              "SubPathString": ""
            },
            {
              "AssetPathName": "/Game/Characters/Player/Female/Medium/Bodies/F_MED_Tie_Dye_Fashion/Skins/F_MED_Tie_Dye_Fashion_Summer/Material/M_F_Tie_Dye_Fashion_Summer_Cloud.M_F_Tie_Dye_Fashion_Summer_Cloud",
              "SubPathString": ""
            },
            {
              "AssetPathName": "/Game/Characters/Player/Female/Medium/Bodies/F_MED_Tie_Dye_Fashion/Skins/F_MED_Tie_Dye_Fashion_Summer/Material/M_F_Tie_Dye_Fashion_Summer_Lime.M_F_Tie_Dye_Fashion_Summer_Lime",
              "SubPathString": ""
            },
            {
              "AssetPathName": "/Game/Characters/Player/Female/Medium/Bodies/F_MED_Tie_Dye_Fashion/Skins/F_MED_Tie_Dye_Fashion_Summer/Material/M_F_Tie_Dye_Fashion_Summer_Zebra.M_F_Tie_Dye_Fashion_Summer_Zebra",
              "SubPathString": ""
            }
          ],
          "ColorParamName": "TieDye_Color_2"
        }
      },
      "VariantChannelName": {
        "Namespace": "",
        "Key": "1516334F4179E77FC9B9E4B4D6197198",
        "SourceString": "Color 2",
        "LocalizedString": "Color 2"
      },
      "VariantChannelTag": {
        "TagName": "Cosmetics.Variant.Channel.RichColor2"
      }
    }
  }
]