[
  {
    "Type": "AthenaPickaxeItemDefinition",
    "Name": "Pickaxe_HeavyRoar",
    "Class": "UScriptClass'AthenaPickaxeItemDefinition'",
    "Flags": "RF_Public | RF_Standalone | RF_Transactional | RF_WasLoaded | RF_LoadCompleted",
    "Properties": {
      "WeaponDefinition": {
        "ObjectName": "FortWeaponMeleeDualWieldItemDefinition'Weapon_Pickaxe_HeavyRoar'",
        "ObjectPath": "/BRCosmetics/Athena/Items/Weapons/Weapon_Pickaxe_HeavyRoar.0"
      },
      "PickaxeImpactFXPreviewOffset": {
        "X": -4.0,
        "Y": 0.0,
        "Z": 52.0
      },
      "PickaxeDualWieldPreviewRotation": {
        "Pitch": 115.0,
        "Yaw": 0.0,
        "Roll": 180.0
      },
      "CameraFramingBounds": {
        "Origin": {
          "X": 0.0,
          "Y": -13.0,
          "Z": -5.0
        },
        "CylinderHalfHeight": 62.0,
        "CylinderRadius": 55.0
      },
      "BaseShotGridId": 63881,
      "ShotGridIds": [
        63881
      ],
      "Rarity": "EFortRarity::Epic",
      "ItemName": {
        "Namespace": "",
        "Key": "81FEF7424DC20DD25914DEA59A07A89F",
        "SourceString": "Shady Double Saw",
        "LocalizedString": "Shady Double Saw"
      },
      "ItemDescription": {
        "Namespace": "",
        "Key": "51F36D094FF1A6272D759FA29C094AA5",
        "SourceString": "Vrnnn-Vrnnn-Vrnnn!!",
        "LocalizedString": "Vrnnn-Vrnnn-Vrnnn!!"
      },
      "ItemShortDescription": {
        "Namespace": "",
        "Key": "CD98F91F45F4F3AF5B2D90BE220D4ADC",
        "SourceString": "Pickaxe",
        "LocalizedString": "Pickaxe"
      },
      "DataList": [
        {
          "MinLevel": 1,
          "MaxLevel": 1
        },
        {
          "Icon": {
            "AssetPathName": "/BRCosmetics/UI/Foundation/Textures/Icons/Weapons/Items/S27/T-Icon-Pickaxes-HeavyRoar.T-Icon-Pickaxes-HeavyRoar",
            "SubPathString": ""
          }
        },
        {
          "LargeIcon": {
            "AssetPathName": "/BRCosmetics/UI/Foundation/Textures/Icons/Weapons/Items/S27/T-Icon-Pickaxes-HeavyRoar-L.T-Icon-Pickaxes-HeavyRoar-L",
            "SubPathString": ""
          }
        },
        {
          "Tags": [
            "Cosmetics.Pickaxe.OneHanded",
            "Cosmetics.Filter.Season.27",
            "Cosmetics.Source.ItemShop",
            "Cosmetics.Set.ThickBottle",
            "Cosmetics.UserFacingFlags.Reactive"
          ]
        },
        {
          "MeshOverride": {
            "AssetPathName": "",
            "SubPathString": ""
          },
          "SkeletalMeshOverride": {
            "AssetPathName": "",
            "SubPathString": ""
          },
          "PivotOffset": {
            "X": 0.0,
            "Y": 0.0,
            "Z": 0.0
          },
          "InitialRotation": {
            "Pitch": 32.0,
            "Yaw": 315.0,
            "Roll": 0.0
          },
          "Scale": 1.0
        },
        {
          "Series": {
            "ObjectName": "FortItemSeriesDefinition'CreatorCollabSeries'",
            "ObjectPath": "/Game/Athena/Items/Cosmetics/Series/CreatorCollabSeries.0"
          }
        },
        {
          "Traits": [
            "Item.Trait.SingleStack"
          ]
        },
        {
          "GeneratedTagsIndexes": [
            552,
            7975,
            545,
            488,
            236,
            357,
            245,
            562,
            162,
            569,
            567,
            166,
            269,
            824,
            113,
            1053,
            442,
            1194,
            1192,
            258,
            1565,
            432,
            1585,
            1921,
            1951,
            2325,
            2470,
            2526,
            2557,
            2563,
            5558,
            5561,
            5573,
            5574,
            5611
          ]
        }
      ]
    }
  }
]