[
  {
    "Type": "AthenaBackpackItemDefinition",
    "Name": "BID_495_PineappleBandit",
    "Class": "UScriptClass'AthenaBackpackItemDefinition'",
    "Flags": "RF_Public | RF_Standalone | RF_Transactional | RF_WasLoaded | RF_LoadCompleted",
    "Properties": {
      "CharacterParts": [
        {
          "ObjectName": "CustomCharacterPart'CP_Backpack_PineappleBandit'",
          "ObjectPath": "/BRCosmetics/Characters/CharacterParts/Backpacks/CP_Backpack_PineappleBandit.1"
        }
      ],
      "Rarity": "EFortRarity::Rare",
      "ItemName": {
        "Namespace": "",
        "Key": "B4466A084EBAED3523A6A2B14E9DF77A",
        "SourceString": "Tropical Stash",
        "LocalizedString": "Tropical Stash"
      },
      "ItemDescription": {
        "Namespace": "",
        "Key": "C25BC003402B666DCBD493BC31A67024",
        "SourceString": "A splash of tropical cash.",
        "LocalizedString": "A splash of tropical cash."
      },
      "ItemShortDescription": {
        "Namespace": "",
        "Key": "03FD5C2B4A4ECC739C30BC8FAC212CC8",
        "SourceString": "Back Bling",
        "LocalizedString": "Back Bling"
      },
      "DataList": [
        {
          "MinLevel": 1,
          "MaxLevel": 1
        },
        {
          "Traits": [
            "Item.Trait.SingleStack"
          ]
        },
        {
          "Icon": {
            "AssetPathName": "/BRCosmetics/UI/Foundation/Textures/Icons/Backpacks/T-Icon-Backpacks-495-PineappleBandit.T-Icon-Backpacks-495-PineappleBandit",
            "SubPathString": ""
          }
        },
        {
          "LargeIcon": {
            "AssetPathName": "/BRCosmetics/UI/Foundation/Textures/Icons/Backpacks/T-Icon-Backpacks-495-PineappleBandit-L.T-Icon-Backpacks-495-PineappleBandit-L",
            "SubPathString": ""
          }
        },
        {
          "Tags": [
            "Cosmetics.Source.ItemShop",
            "Cosmetics.Filter.Season.12",
            "Cosmetics.Set.AppleThief"
          ]
        },
        {
          "GeneratedTagsIndexes": [
            115,
            549,
            552,
            7975,
            545,
            229,
            2,
            488,
            236,
            544,
            553,
            540,
            8,
            46,
            237,
            596,
            243,
            613,
            269,
            14,
            542,
            665,
            682,
            247,
            705,
            704,
            736,
            932,
            1894,
            845,
            893,
            436,
            950,
            986,
            1053,
            1120,
            539,
            1508
          ]
        }
      ]
    }
  }
]